{
  "name": "Sentinel Bisect",
  "image": "mcr.microsoft.com/devcontainers/python:3.11",
  "postCreateCommand": "python -m venv .venv && . .venv/bin/activate && pip install -r requirements.txt && pip install -e . && cp -n .env.example .env && python fixtures/build_fixture.py",
  "postAttachCommand": "echo 'Environment ready. Try: source .venv/bin/activate && sentinel-bisect --repo fixtures/flaky-regression-demo --command \"pytest -q tests/test_calculator.py\" --serve'",
  "forwardPorts": [8787],
  "portsAttributes": {
    "8787": {
      "label": "Sentinel Bisect timeline",
      "onAutoForward": "notify"
    }
  },
  "customizations": {
    "vscode": {
      "extensions": ["ms-python.python"]
    }
  }
}
